torchfurnace/__init__.py
torchfurnace/engine.py
torchfurnace/image2lmdb.py
torchfurnace/options.py
torchfurnace/tracer.py
torchfurnace/utils/__init__.py
torchfurnace/utils/function.py
torchfurnace/utils/meter.py
torchfurnace/utils/torch_summary.py
torchfurnace/utils/tracer_component.py
torchfurnace-0.1.2.dist-info/LICENSE
torchfurnace-0.1.2.dist-info/METADATA
torchfurnace-0.1.2.dist-info/WHEEL
torchfurnace-0.1.2.dist-info/top_level.txt
torchfurnace-0.1.2.dist-info/RECORD
