Metadata-Version: 2.1
Name: torchfurnace
Version: 0.1.2
Summary: A tool package for training model, pre-processing dataset and managing experiment record in pytorch AI tasks.
Home-page: https://github.com/tianyu-su/torchfurnace
Author: TianyuSu
Author-email: tyanyu.su@gmail.com
Maintainer: TianyuSu
Maintainer-email: tyanyu.su@gmail.com
License: MIT License
Keywords: pytorch,tracer,engine,torchfurnace
Platform: any
Classifier: Programming Language :: Python :: 3.6
Classifier: License :: OSI Approved :: MIT License
Classifier: Operating System :: OS Independent
Requires-Python: >=3.6
Requires-Dist: numpy (>=1.18.1)
Requires-Dist: tqdm (>=4.42.1)
Requires-Dist: lmdb (>=0.98)
Requires-Dist: torch (>=1.3.1)
Requires-Dist: torchvision (>=0.4.2)
Requires-Dist: pyarrow (>=0.11.1)
Requires-Dist: six (>=1.14.0)
Requires-Dist: Pillow (>=6.1.0)
Requires-Dist: tensorboard (>=2.1.0)
